spextra/__init__.py
spextra/configuration.py
spextra/containers.py
spextra/data/__init__.py
spextra/data/config.yml
spextra/data/config_defaults.yml
spextra/data/spextra_registry.txt
spextra/data/svo/2MASS/2MASS.H
spextra/data/svo/2MASS/2MASS.J
spextra/data/svo/2MASS/2MASS.Ks
spextra/data/svo/GTC/OSIRIS
spextra/data/svo/GTC/OSIRIS.F643
spextra/data/svo/GTC/OSIRIS.F643_filter
spextra/data/svo/GTC/OSIRIS.F648
spextra/data/svo/GTC/OSIRIS.F648_filter
spextra/data/svo/GTC/OSIRIS.F657
spextra/data/svo/GTC/OSIRIS.F657_filter
spextra/data/svo/GTC/OSIRIS.F666
spextra/data/svo/GTC/OSIRIS.F666_filter
spextra/data/svo/GTC/OSIRIS.F680
spextra/data/svo/GTC/OSIRIS.F680_filter
spextra/data/svo/GTC/OSIRIS.F694
spextra/data/svo/GTC/OSIRIS.F694_filter
spextra/data/svo/GTC/OSIRIS.F709
spextra/data/svo/GTC/OSIRIS.F709_filter
spextra/data/svo/GTC/OSIRIS.F723
spextra/data/svo/GTC/OSIRIS.F723_filter
spextra/data/svo/GTC/OSIRIS.F738
spextra/data/svo/GTC/OSIRIS.F738_filter
spextra/data/svo/GTC/OSIRIS.F754
spextra/data/svo/GTC/OSIRIS.F754_filter
spextra/data/svo/GTC/OSIRIS.F770
spextra/data/svo/GTC/OSIRIS.F770_filter
spextra/data/svo/GTC/OSIRIS.F785
spextra/data/svo/GTC/OSIRIS.F785_filter
spextra/data/svo/GTC/OSIRIS.F802
spextra/data/svo/GTC/OSIRIS.F802_filter
spextra/data/svo/GTC/OSIRIS.F819
spextra/data/svo/GTC/OSIRIS.F819_filter
spextra/data/svo/GTC/OSIRIS.F838
spextra/data/svo/GTC/OSIRIS.F838_filter
spextra/data/svo/GTC/OSIRIS.F858
spextra/data/svo/GTC/OSIRIS.F858_filter
spextra/data/svo/GTC/OSIRIS.F878
spextra/data/svo/GTC/OSIRIS.F878_filter
spextra/data/svo/GTC/OSIRIS.F893
spextra/data/svo/GTC/OSIRIS.F893_filter
spextra/data/svo/GTC/OSIRIS.F902
spextra/data/svo/GTC/OSIRIS.F902_filter
spextra/data/svo/GTC/OSIRIS.F911
spextra/data/svo/GTC/OSIRIS.F911_filter
spextra/data/svo/GTC/OSIRIS.F919
spextra/data/svo/GTC/OSIRIS.F919_filter
spextra/data/svo/GTC/OSIRIS.F924
spextra/data/svo/GTC/OSIRIS.F924_filter
spextra/data/svo/GTC/OSIRIS.F927
spextra/data/svo/GTC/OSIRIS.F927_filter
spextra-0.43.1.dist-info/METADATA
spextra-0.43.1.dist-info/WHEEL
spextra-0.43.1.dist-info/licenses/LICENSE
spextra-0.43.1.dist-info/RECORD
