Metadata-Version: 2.4
Name: speXtra
Version: 0.43.1
Summary: Tool to manage and manipulate astronomical spectra.
License: MIT
License-File: LICENSE
Keywords: astronomy
Author: Miguel Verdugo
Author-email: mverduol@gmail.com
Maintainer: Kieran Leschinski
Maintainer-email: kieran.leschinski@unive.ac.at
Requires-Python: >=3.10,<3.15
Classifier: Intended Audience :: Science/Research
Classifier: License :: OSI Approved :: MIT License
Classifier: Operating System :: OS Independent
Classifier: Programming Language :: Python :: 3
Classifier: Programming Language :: Python :: 3.10
Classifier: Programming Language :: Python :: 3.11
Classifier: Programming Language :: Python :: 3.12
Classifier: Programming Language :: Python :: 3.13
Classifier: Programming Language :: Python :: 3.14
Classifier: Topic :: Scientific/Engineering :: Astronomy
Requires-Dist: astar-utils (>=0.5.0,<1.0)
Requires-Dist: astropy (>=6.1.7,<8.0.0)
Requires-Dist: more-itertools (>=10.2.0,<11.0.0)
Requires-Dist: numpy (>=1.26.4,<2.3.0) ; python_version >= "3.10" and python_version < "3.13"
Requires-Dist: numpy (>=2.2.6,<3.0.0) ; python_version >= "3.13"
Requires-Dist: pooch (>=1.8.2,<2.0.0)
Requires-Dist: pyyaml (>=6.0.3,<7.0.0)
Requires-Dist: scipy (>=1.15.3,<1.16.0) ; python_version == "3.10"
Requires-Dist: scipy (>=1.17.0,<1.18.0) ; python_version >= "3.11"
Requires-Dist: synphot (>=1.6.1,<2.0.0)
Requires-Dist: tqdm (>=4.67.1,<5.0.0)
Project-URL: Bug Tracker, https://github.com/AstarVienna/speXtra/issues
Project-URL: Changelog, https://github.com/AstarVienna/speXtra/blob/main/CHANGELOG.md
Project-URL: Documentation, https://spextra.readthedocs.io/en/stable/
Project-URL: Repository, https://github.com/AstarVienna/speXtra
